gastimator/__init__.py
gastimator/corner_plot.py
gastimator/gastimator.py
gastimator/priors.py
gastimator-0.5.2.dist-info/LICENSE
gastimator-0.5.2.dist-info/METADATA
gastimator-0.5.2.dist-info/WHEEL
gastimator-0.5.2.dist-info/top_level.txt
gastimator-0.5.2.dist-info/RECORD
