Metadata-Version: 2.1
Name: gastimator
Version: 0.5.2
Summary: Implementation of a Python MCMC gibbs-sampler with adaptive stepping
Home-page: https://github.com/TimothyADavis/GAStimator
Author: Timothy A. Davis
Author-email: DavisT@cardiff.ac.uk
License: GNU GPLv3
Classifier: Development Status :: 3 - Alpha
Classifier: License :: OSI Approved :: GNU General Public License v3 (GPLv3)
Classifier: Programming Language :: Python :: 3
Classifier: Operating System :: OS Independent
License-File: LICENSE
Requires-Dist: numpy
Requires-Dist: matplotlib
Requires-Dist: tqdm (>=4.66.4)
Requires-Dist: plotbin
Requires-Dist: joblib (>=1.1.1)
